dsl2_probability/Binomialdistribution.py
dsl2_probability/Gaussiandistribution.py
dsl2_probability/Generaldistribution.py
dsl2_probability/__init__.py
dsl2_probability-1.3.dist-info/METADATA
dsl2_probability-1.3.dist-info/WHEEL
dsl2_probability-1.3.dist-info/top_level.txt
dsl2_probability-1.3.dist-info/RECORD
