Metadata-Version: 2.1
Name: dsl2-probability
Version: 1.3
Summary: Gaussian and Binomial distributions
Home-page: UNKNOWN
Author: Alexandra Jaber
Author-email: alexandra.jaber@vodafone.com
License: UNKNOWN
Platform: UNKNOWN
